{
  "height": "Бойы",
  "height_unit": "cm",
  "weight": "Салмағы",
  "weight_unit": "kg",
  "bmi": "BMI",
  "bmi_normal": "Қалыпты",
  "age": "Жасы",
  "age_unit": "жас",
  "body_data": "Дене деректері",
  "edit_body_data": "Өңдеу",
  "subscribe_title": "Мүшелік",
  "subscribe_subtitle": "Барлық премиум мүмкіндіктерді ашу",
  "theme_setting": "Тақырып",
  "language": "Тіл",
  "language_title": "Тіл",
  "language_english": "English",
  "language_english_subtitle": "Ағылшын",
  "language_chinese": "中文(简体)",
  "language_chinese_subtitle": "Қытай (жеңілдетілген)",
  "follow_system": "Жүйе бойынша",
  "follow_system_subtitle": "Құрылғы тілін пайдалану",
  "language_option_en": "Ағылшын",
  "language_option_zh_hans": "Қытай (жеңілдетілген)",
  "language_option_zh_hant": "Қытай (дәстүрлі)",
  "language_option_ar": "Араб",
  "language_option_de": "Неміс",
  "language_option_es": "Испан",
  "language_option_fr": "Француз",
  "language_option_id": "Индонезия",
  "language_option_it": "Итальян",
  "language_option_ja": "Жапон",
  "language_option_kk": "Қазақ",
  "language_option_ko": "Корей",
  "language_option_pl": "Поляк",
  "language_option_pt": "Португал",
  "language_option_ru": "Орыс",
  "language_option_th": "Тай",
  "language_option_tr": "Түрік",
  "language_option_vi": "Вьетнам",
  "share_app": "Бөлісу",
  "share_app_subject": "Пайдалы қадам санағыш қолданба",
  "share_app_content": "Мен осы қадам санағыш қолданбасымен күн сайын қадамдарым мен жаттығуларымды есептеймін. Бірге қосыл!",
  "rate_us": "Бағалау",
  "suggestion": "Ұсыныс",
  "rate_dialog_title": "Қолданба ұнай ма?",
  "rate_dialog_message": "Сіздің бағаңыз — біздің ең үлкен ынтамыз. Бағалау үшін жұлдызшаларды басыңыз.",
  "rate_dialog_submit": "Жіберу",
  "suggestion_title": "Ұсыныс",
  "suggestion_email_label": "Электрондық пошта",
  "suggestion_email_hint": "Поштаңызды енгізіңіз",
  "suggestion_subject_label": "Тақырыбы",
  "suggestion_subject_hint": "Тақырыпты енгізіңіз",
  "suggestion_message_label": "Толығырақ",
  "suggestion_message_hint": "Ұсынысыңызды немесе кездескен мәселені сипаттаңыз",
  "suggestion_send": "Жіберу",
  "suggestion_success": "Пікіріңізге рахмет!",
  "suggestion_field_required": "Барлық өрістерді толтырыңыз",
  "suggestion_invalid_email": "Жарамды пошта енгізіңіз",
  "suggestion_send_failed": "Жіберілмеді, қайталап көріңіз",
  "user_agreement": "Пайдаланушы келісімі",
  "privacy_policy": "Құпиялылық саясаты",
  "about_us": "Қолданба туралы",
  "version": "Нұсқа",
  "bmi_low": "Төмен",
  "bmi_high": "Жоғары",
  "bmi_obese": "Семіздік",
  "edit_body_data_title": "Дене деректерін өңдеу",
  "save": "Сақтау",
  "invalid_input": "Қате енгізу",
  "invalid_body_data_input_message": "Ауқымдарды тексеріп, қайта көріңіз.",
  "height_input_hint": "120 - 220",
  "height_range_hint": "Ауқым: 120 - 220 cm",
  "weight_input_hint": "30 - 200",
  "weight_range_hint": "Ауқым: 30 - 200 kg",
  "age_input_hint": "1 - 120",
  "age_range_hint": "Ауқым: 1 - 120",
  "bmi_formula": "BMI = Салмақ(kg) / Бой^2(m)",
  "tip_title": "Кеңес",
  "body_data_tip": "Дене деректері калория шығынын, денсаулық талдауын және жеке кеңестерді есептеуге қолданылады. Деректерді дәл сақтаңыз."
}
